Metadata-Version: 1.0
Name: cmsync
Version: 0.8.1
Summary: A simple module to sync local folders that can run commands after the transfer.
Home-page: https://github.com/codeminus/cmsync
Author: Wilson Santos
Author-email: wilson@codeminus.org
License: Apache License 2.0
Keywords: codeminus sync transfer
Platform: UNKNOWN
